pgvector_azure_openai_mcp_server/__init__.py
pgvector_azure_openai_mcp_server/__main__.py
pgvector_azure_openai_mcp_server/cli.py
pgvector_azure_openai_mcp_server/config.py
pgvector_azure_openai_mcp_server/database.py
pgvector_azure_openai_mcp_server/exceptions.py
pgvector_azure_openai_mcp_server/server.py
pgvector_azure_openai_mcp_server/models/__init__.py
pgvector_azure_openai_mcp_server/models/collection.py
pgvector_azure_openai_mcp_server/models/vector_record.py
pgvector_azure_openai_mcp_server/services/__init__.py
pgvector_azure_openai_mcp_server/services/chunking_service.py
pgvector_azure_openai_mcp_server/services/collection_service.py
pgvector_azure_openai_mcp_server/services/document_service.py
pgvector_azure_openai_mcp_server/services/embedding_service.py
pgvector_azure_openai_mcp_server/services/vector_service.py
pgvector_azure_openai_mcp_server/services/parsers/__init__.py
pgvector_azure_openai_mcp_server/services/parsers/base_parser.py
pgvector_azure_openai_mcp_server/services/parsers/csv_parser.py
pgvector_azure_openai_mcp_server/services/parsers/pdf_parser.py
pgvector_azure_openai_mcp_server/services/parsers/text_parser.py
pgvector_azure_openai_mcp_server/utils/__init__.py
pgvector_azure_openai_mcp_server/utils/encoding.py
pgvector_azure_openai_mcp_server/utils/formatters.py
pgvector_azure_openai_mcp_server/utils/validators.py
pgvector_azure_openai_mcp_server-1.0.4.dist-info/METADATA
pgvector_azure_openai_mcp_server-1.0.4.dist-info/WHEEL
pgvector_azure_openai_mcp_server-1.0.4.dist-info/entry_points.txt
pgvector_azure_openai_mcp_server-1.0.4.dist-info/RECORD
