Metadata-Version: 2.4
Name: pgvector-azure-openai-mcp-server
Version: 1.0.4
Summary: An MCP server with RAG capabilities using Azure OpenAI embeddings and pgvector for PostgreSQL.
Author-email: Derzsi Dániel <daniel@tohka.us>
License: MIT
Requires-Python: >=3.11
Requires-Dist: chardet>=5.2.0
Requires-Dist: langchain-azure-ai>=1.0.0
Requires-Dist: langchain-text-splitters>=1.0.0
Requires-Dist: mcp>=1.18.0
Requires-Dist: numpy>=2.3.4
Requires-Dist: pandas>=2.3.3
Requires-Dist: pgvector>=0.4.1
Requires-Dist: psycopg2-binary>=2.9.11
Requires-Dist: pydantic-settings>=2.11.0
Requires-Dist: pydantic>=2.12.3
Requires-Dist: pymupdf4llm>=0.0.27
Requires-Dist: python-dotenv>=1.1.1
Requires-Dist: sqlalchemy>=2.0.44
Provides-Extra: dev
Requires-Dist: mypy>=1.18.2; extra == 'dev'
Requires-Dist: pytest-cov>=7.0.0; extra == 'dev'
Requires-Dist: pytest-mock>=3.15.1; extra == 'dev'
Requires-Dist: pytest>=8.4.2; extra == 'dev'
Requires-Dist: ruff>=0.14.1; extra == 'dev'
